{
  "main": {
    "id": "d5cec0f9e28acf2b",
    "type": "split",
    "children": [
      {
        "id": "dfe166dbd269c893",
        "type": "tabs",
        "children": [
          {
            "id": "f01ec3ead760ed66",
            "type": "leaf",
            "state": {
              "type": "markdown",
              "state": {
                "file": "Charms/Lunar/Charisma/Influence/Enraged Predator’s Howl.md",
                "mode": "source",
                "source": false,
                "backlinks": true,
                "backlinkOpts": {
                  "collapseAll": false,
                  "extraContext": false,
                  "sortOrder": "alphabetical",
                  "showSearch": false,
                  "searchQuery": "",
                  "backlinkCollapsed": true,
                  "unlinkedCollapsed": true
                }
              },
              "icon": "lucide-file",
              "title": "Enraged Predator’s Howl"
            }
          },
          {
            "id": "2620b2898567d939",
            "type": "leaf",
            "state": {
              "type": "markdown",
              "state": {
                "file": "Sorceries/Archetypes/Soul-Perfecting Elixir/Soul-Perfecting Elixir.md",
                "mode": "source",
                "source": false,
                "backlinks": false
              },
              "icon": "lucide-file",
              "title": "Soul-Perfecting Elixir"
            }
          },
          {
            "id": "151e567cbb54436b",
            "type": "leaf",
            "state": {
              "type": "markdown",
              "state": {
                "file": "Character Creation/Lunar Exalted.md",
                "mode": "source",
                "source": false,
                "backlinks": true,
                "backlinkOpts": {
                  "collapseAll": false,
                  "extraContext": false,
                  "sortOrder": "alphabetical",
                  "showSearch": false,
                  "searchQuery": "",
                  "backlinkCollapsed": false,
                  "unlinkedCollapsed": true
                }
              },
              "icon": "lucide-file",
              "title": "Lunar Exalted"
            }
          },
          {
            "id": "dc76a3360dd0bc8d",
            "type": "leaf",
            "state": {
              "type": "markdown",
              "state": {
                "file": "Character Creation/My Characters/Lunar Character.md",
                "mode": "source",
                "source": false,
                "backlinks": false
              },
              "icon": "lucide-file",
              "title": "Lunar Character"
            }
          },
          {
            "id": "717233dcb784abf2",
            "type": "leaf",
            "state": {
              "type": "markdown",
              "state": {
                "file": "Character Creation/My Characters/Abyssal Character.md",
                "mode": "source",
                "source": false,
                "backlinks": false
              },
              "icon": "lucide-file",
              "title": "Abyssal Character"
            }
          },
          {
            "id": "546a801e374d12fc",
            "type": "leaf",
            "state": {
              "type": "empty",
              "state": {},
              "icon": "lucide-file",
              "title": "New tab"
            }
          }
        ],
        "currentTab": 1
      },
      {
        "id": "a25caee605a100db",
        "type": "tabs",
        "children": [
          {
            "id": "d7aa323a838a90c1",
            "type": "leaf",
            "state": {
              "type": "markdown",
              "state": {
                "file": "Character Advancement.md",
                "mode": "source",
                "source": false,
                "backlinks": false
              },
              "icon": "lucide-file",
              "title": "Character Advancement"
            }
          }
        ]
      }
    ],
    "direction": "vertical"
  },
  "left": {
    "id": "9bc4d08a68799cf7",
    "type": "split",
    "children": [
      {
        "id": "07975790ae996fdb",
        "type": "tabs",
        "children": [
          {
            "id": "3a5d214276320e48",
            "type": "leaf",
            "state": {
              "type": "file-explorer",
              "state": {
                "sortOrder": "byCreatedTimeReverse",
                "autoReveal": false
              },
              "icon": "lucide-folder-closed",
              "title": "Files"
            }
          },
          {
            "id": "654ff318f4cd4494",
            "type": "leaf",
            "state": {
              "type": "search",
              "state": {
                "query": "",
                "matchingCase": false,
                "explainSearch": false,
                "collapseAll": false,
                "extraContext": false,
                "sortOrder": "byCreatedTimeReverse"
              },
              "icon": "lucide-search",
              "title": "Search"
            }
          },
          {
            "id": "59aad9b80729329d",
            "type": "leaf",
            "state": {
              "type": "bookmarks",
              "state": {},
              "icon": "lucide-bookmark",
              "title": "Bookmarks"
            }
          }
        ]
      }
    ],
    "direction": "horizontal",
    "width": 323.5
  },
  "right": {
    "id": "d3f03f9e2c185d65",
    "type": "split",
    "children": [
      {
        "id": "7e9ef189849b1725",
        "type": "tabs",
        "children": [
          {
            "id": "f681cbbf25eaff6e",
            "type": "leaf",
            "state": {
              "type": "backlink",
              "state": {
                "file": "Lunar Shapeshifting/Sacred Hunt.md",
                "collapseAll": false,
                "extraContext": false,
                "sortOrder": "alphabetical",
                "showSearch": true,
                "searchQuery": "",
                "backlinkCollapsed": false,
                "unlinkedCollapsed": true
              },
              "icon": "links-coming-in",
              "title": "Backlinks for Sacred Hunt"
            }
          },
          {
            "id": "ac35b303648da84c",
            "type": "leaf",
            "state": {
              "type": "outgoing-link",
              "state": {
                "file": "Lunar Shapeshifting/Sacred Hunt.md",
                "linksCollapsed": false,
                "unlinkedCollapsed": true
              },
              "icon": "links-going-out",
              "title": "Outgoing links from Sacred Hunt"
            }
          },
          {
            "id": "2cb6185f52419552",
            "type": "leaf",
            "state": {
              "type": "tag",
              "state": {
                "sortOrder": "frequency",
                "useHierarchy": true,
                "showSearch": false,
                "searchQuery": ""
              },
              "icon": "lucide-tags",
              "title": "Tags"
            }
          },
          {
            "id": "c8687db642245369",
            "type": "leaf",
            "state": {
              "type": "outline",
              "state": {
                "file": "Lunar Shapeshifting/Sacred Hunt.md",
                "followCursor": false,
                "showSearch": false,
                "searchQuery": ""
              },
              "icon": "lucide-list",
              "title": "Outline of Sacred Hunt"
            }
          },
          {
            "id": "19b2474784eea866",
            "type": "leaf",
            "state": {
              "type": "all-properties",
              "state": {
                "sortOrder": "frequency",
                "showSearch": true,
                "searchQuery": ""
              },
              "icon": "lucide-archive",
              "title": "All properties"
            }
          },
          {
            "id": "1de4e1116e1d7f9c",
            "type": "leaf",
            "state": {
              "type": "file-properties",
              "state": {
                "file": "Lunar Shapeshifting/Sacred Hunt.md"
              },
              "icon": "lucide-info",
              "title": "File properties for Sacred Hunt"
            }
          },
          {
            "id": "1a8c5271dfe7db8a",
            "type": "leaf",
            "state": {
              "type": "BC-matrix",
              "state": {},
              "icon": "lucide-file",
              "title": "Plugin no longer active"
            }
          },
          {
            "id": "19dfe583876070d4",
            "type": "leaf",
            "state": {
              "type": "BC-tree",
              "state": {},
              "icon": "lucide-file",
              "title": "Plugin no longer active"
            }
          }
        ]
      }
    ],
    "direction": "horizontal",
    "width": 326.5,
    "collapsed": true
  },
  "left-ribbon": {
    "hiddenItems": {
      "switcher:Open quick switcher": false,
      "graph:Open graph view": false,
      "canvas:Create new canvas": false,
      "templates:Insert template": false,
      "command-palette:Open command palette": false
    }
  },
  "active": "d7aa323a838a90c1",
  "lastOpenFiles": [
    "Thaumaturgic Rituals/Speak with Ozashun.md",
    "Thaumaturgic Rituals/Tear-Stained Talisman.md",
    "Thaumaturgic Rituals/Unquenchable Flame.md",
    "Thaumaturgic Rituals/Breath of Unlife.md",
    "Thaumaturgic Rituals/Reading the Tea Leaves.md",
    "Thaumaturgic Rituals/Final Testament.md",
    "Character Advancement.md",
    "Rules Reference/Excellencies.md",
    "Sorceries/Archetypes/Soul-Perfecting Elixir/Soul-Perfecting Elixir.md",
    "Charms/Lunar/Lunar Excellency.md",
    "Charms/Lunar/Excellent Lunar Strength.md",
    "Charms/Lunar/Excellent Lunar Stamina.md",
    "Charms/Lunar/Charisma/Influence/Captivating Siren Voice.md",
    "Charms/Lunar/Charisma/Influence/Beast-God Idolatry.md",
    "Charms/Lunar/Charisma/Influence/Argent Glyph Enchantment.md",
    "Traits/Willpower.md",
    "Sorceries/Archetypes/Scarred by Nightmares/Scarred by Nightmares.md",
    "Sorceries/Archetypes/Witch-Beast Pact/Witch-Beast Pact.md",
    "Sorceries/Archetypes/The Path of Celestial Design/The Path of Celestial Design.md",
    "Sorceries/Archetypes/Simendor Sorcery/Simendor Sorcery.md",
    "Sorceries/Archetypes/The Talisman of Ten Thousand Eyes/The Talisman of Ten Thousand Eyes.md",
    "Sorceries/Archetypes/Pact with an Ifrit Lord/Pact with an Ifrit Lord.md",
    "Sorceries/Archetypes/Bargain with Mara/Bargain with Mara.md",
    "Sorceries/Archetypes/Dreamer of the Caul/Dreamer of the Caul.md",
    "Items/Artifacts & Evocations/Arms of the Chosen/Weapons/Courante and Galliard/Courante and Galliard.md",
    "Items/Artifacts & Evocations/Arms of the Chosen/Misc/Arete/Arete.md",
    "Lore/Lore Sidebars/Dragon-Blooded Book",
    "Character Creation/My Characters",
    "Charms/Abyssal/Performance/Universal",
    "Lore/Factions/Minor Factions",
    "Lore/Factions/Regional Factions/Minor Factions",
    "Lore/Factions/Subfactions",
    "Lore/Factions/Minor or Regional",
    "Lore/Factions",
    "Lore/Notable Individuals/Shahan-yas",
    "Lore/Locations",
    "Charms/Solar/Archery/Solar Archery Charm Tree.canvas",
    "Charms/Martial Arts/Righteous Devil Style/Righteous Devil Style.canvas",
    "Charms/Martial Arts/Black Claw Style/Black Claw Charm Tree.canvas",
    "Charms/Martial Arts/Mantis Style/Mantis Style.canvas",
    "Charms/Martial Arts/Immaculate Dragon Styles/Fire Dragon Style/Fire Dragon Style.canvas",
    "Charms/Martial Arts/Immaculate Dragon Styles/Air Dragon Style/Air Dragon Tree.canvas",
    "Charms/Martial Arts/Golden Janissary Style/Golden Janissary Style.canvas",
    "Charms/Martial Arts/Crane Style/Crane Charm Tree.canvas",
    "Charms/Martial Arts/Dreaming Pearl Courtesan Style/Dreaming Pearl Courtesan Tree.canvas",
    "Charms/Dragon-Blooded/Melee/Dragon-Blooded Melee Charm Tree.canvas"
  ]
}